Metadata-Version: 2.1
Name: requests-base-url
Version: 0.1.0
Summary: Http client with base_url base on requests
Home-page: https://github.com/hanzhichao/requests-base-url
Author: Han Zhichao
Author-email: superhin@126.com
License: MIT license
Keywords: base_url,requests,http client
Classifier: Programming Language :: Python
Classifier: Programming Language :: Python :: 3.7
License-File: LICENSE
Requires-Dist: requests
